{"scrutin": {"@xmlns": "http://schemas.assemblee-nationale.fr/referentiel", "@xmlns:xsi": "http://www.w3.org/2001/XMLSchema-instance", "uid": "VTANR5L17V7399", "numero": "7399", "organeRef": "PO838901", "legislature": "17", "sessionRef": "SCR5A2026O1", "seanceRef": "RUANR5L17S2026IDS30718", "dateScrutin": "2026-06-15", "quantiemeJourSeance": "1", "typeVote": {"codeTypeVote": "SPO", "libelleTypeVote": "scrutin public ordinaire", "typeMajorite": "Majorit\u00e9 absolue des suffrages exprim\u00e9s"}, "sort": {"code": "adopt\u00e9", "libelle": "l'Assembl\u00e9e nationale a adopt\u00e9"}, "titre": "l'article premier du projet de loi portant habilitation de l'assembl\u00e9e de Martinique \u00e0 fixer des r\u00e8gles applicables sur son territoire en application de l'article 73 de la Constitution en mati\u00e8re d'\u00e9nergie, d'eau et d'assainissement (premi\u00e8re lecture).", "demandeur": {"texte": "Pr\u00e9sidente du groupe \"Rassemblement National\"", "referenceLegislative": null}, "objet": {"libelle": "l'article premier du projet de loi portant habilitation de l'assembl\u00e9e de Martinique \u00e0 fixer des r\u00e8gles applicables sur son territoire en application de l'article 73 de la Constitution en mati\u00e8re d'\u00e9nergie, d'eau et d'assainissement (premi\u00e8re lecture).", "dossierLegislatif": {"libelle": "Projet de loi portant habilitation de l\u2019assembl\u00e9e de Martinique \u00e0 fixer elle-m\u00eame des r\u00e8gles applicables sur son territoire en application de l\u2019article 73 de la Constitution en mati\u00e8re d\u2019\u00e9nergie, d\u2019eau et d\u2019assainissement", "dossierRef": "DLR5L17N53600"}, "referenceLegislative": null}, "modePublicationDesVotes": "DecompteNominatif", "syntheseVote": {"nombreVotants": "39", "suffragesExprimes": "39", "nbrSuffragesRequis": "20", "annonce": "l'Assembl\u00e9e nationale a adopt\u00e9", "decompte": {"nonVotants": "2", "pour": "39", "contre": "0", "abstentions": "0", "nonVotantsVolontaires": "0"}}, "ventilationVotes": {"organe": {"organeRef": "PO838901", "groupes": {"groupe": [{"organeRef": "PO845401", "nombreMembresGroupe": "122", "vote": {"positionMajoritaire": "pour", "decompteVoix": {"nonVotants": "1", "pour": "5", "contre": "0", "abstentions": "0", "nonVotantsVolontaires": "0"}, "decompteNominatif": {"nonVotants": {"votant": {"acteurRef": "PA720468", "mandatRef": "PM840333", "parDelegation": "false", "numPlace": "027", "causePositionVote": "PSE"}}, "pours": {"votant": [{"acteurRef": "PA793832", "mandatRef": "PM842678", "parDelegation": "false", "numPlace": "126"}, {"acteurRef": "PA841059", "mandatRef": "PM880630", "parDelegation": "false", "numPlace": "080"}, {"acteurRef": "PA841873", "mandatRef": "PM843434", "parDelegation": "false", "numPlace": "122"}, {"acteurRef": "PA841825", "mandatRef": "PM843392", "parDelegation": "false", "numPlace": "071"}, {"acteurRef": "PA841613", "mandatRef": "PM843170", "parDelegation": "false", "numPlace": "144"}]}, "contres": null, "abstentions": null}}}, {"organeRef": "PO845407", "nombreMembresGroupe": "91", "vote": {"positionMajoritaire": "pour", "decompteVoix": {"nonVotants": "1", "pour": "7", "contre": "0", "abstentions": "0", "nonVotantsVolontaires": "0"}, "decompteNominatif": {"nonVotants": {"votant": {"acteurRef": "PA721908", "mandatRef": "PM843467", "parDelegation": "false", "numPlace": "391", "causePositionVote": "PAN"}}, "pours": {"votant": [{"acteurRef": "PA721764", "mandatRef": "PM843416", "parDelegation": "true", "numPlace": "271"}, {"acteurRef": "PA794802", "mandatRef": "PM843191", "parDelegation": "false", "numPlace": "364"}, {"acteurRef": "PA643184", "mandatRef": "PM843206", "parDelegation": "false", "numPlace": "366"}, {"acteurRef": "PA720022", "mandatRef": "PM842957", "parDelegation": "false", "numPlace": "294"}, {"acteurRef": "PA794206", "mandatRef": "PM842879", "parDelegation": "false", "numPlace": "307"}, {"acteurRef": "PA795050", "mandatRef": "PM874601", "parDelegation": "true", "numPlace": "312"}, {"acteurRef": "PA795954", "mandatRef": "PM874940", "parDelegation": "false", "numPlace": "322"}]}, "contres": null, "abstentions": null}}}, {"organeRef": "PO845413", "nombreMembresGroupe": "71", "vote": {"positionMajoritaire": "pour", "decompteVoix": {"nonVotants": "0", "pour": "7", "contre": "0", "abstentions": "0", "nonVotantsVolontaires": "0"}, "decompteNominatif": {"nonVotants": null, "pours": {"votant": [{"acteurRef": "PA794906", "mandatRef": "PM843284", "parDelegation": "false", "numPlace": "544"}, {"acteurRef": "PA842187", "mandatRef": "PM843704", "parDelegation": "false", "numPlace": "595"}, {"acteurRef": "PA795844", "mandatRef": "PM843515", "parDelegation": "false", "numPlace": "546"}, {"acteurRef": "PA793744", "mandatRef": "PM842696", "parDelegation": "false", "numPlace": "561"}, {"acteurRef": "PA610654", "mandatRef": "PM843719", "parDelegation": "false", "numPlace": "632"}, {"acteurRef": "PA720892", "mandatRef": "PM840420", "parDelegation": "false", "numPlace": "623"}, {"acteurRef": "PA796062", "mandatRef": "PM843668", "parDelegation": "false", "numPlace": "633"}]}, "contres": null, "abstentions": null}}}, {"organeRef": "PO845419", "nombreMembresGroupe": "68", "vote": {"positionMajoritaire": "pour", "decompteVoix": {"nonVotants": "0", "pour": "4", "contre": "0", "abstentions": "0", "nonVotantsVolontaires": "0"}, "decompteNominatif": {"nonVotants": null, "pours": {"votant": [{"acteurRef": "PA795762", "mandatRef": "PM843767", "parDelegation": "false", "numPlace": "437"}, {"acteurRef": "PA841381", "mandatRef": "PM842966", "parDelegation": "false", "numPlace": "463"}, {"acteurRef": "PA794270", "mandatRef": "PM842972", "parDelegation": "false", "numPlace": "452"}, {"acteurRef": "PA840955", "mandatRef": "PM842573", "parDelegation": "false", "numPlace": "444"}]}, "contres": null, "abstentions": null}}}, {"organeRef": "PO845425", "nombreMembresGroupe": "48", "vote": {"positionMajoritaire": "pour", "decompteVoix": {"nonVotants": "0", "pour": "3", "contre": "0", "abstentions": "0", "nonVotantsVolontaires": "0"}, "decompteNominatif": {"nonVotants": null, "pours": {"votant": [{"acteurRef": "PA718884", "mandatRef": "PM842420", "parDelegation": "true", "numPlace": "199"}, {"acteurRef": "PA794750", "mandatRef": "PM881146", "parDelegation": "false", "numPlace": "196"}, {"acteurRef": "PA842121", "mandatRef": "PM874932", "parDelegation": "false", "numPlace": "184"}]}, "contres": null, "abstentions": null}}}, {"organeRef": "PO845439", "nombreMembresGroupe": "38", "vote": {"positionMajoritaire": "pour", "decompteVoix": {"nonVotants": "0", "pour": "3", "contre": "0", "abstentions": "0", "nonVotantsVolontaires": "0"}, "decompteNominatif": {"nonVotants": null, "pours": {"votant": [{"acteurRef": "PA842013", "mandatRef": "PM843563", "parDelegation": "false", "numPlace": "541"}, {"acteurRef": "PA795808", "mandatRef": "PM843644", "parDelegation": "true", "numPlace": "499"}, {"acteurRef": "PA2940", "mandatRef": "PM842531", "parDelegation": "false", "numPlace": "495"}]}, "contres": null, "abstentions": null}}}, {"organeRef": "PO845454", "nombreMembresGroupe": "37", "vote": {"positionMajoritaire": "pour", "decompteVoix": {"nonVotants": "0", "pour": "3", "contre": "0", "abstentions": "0", "nonVotantsVolontaires": "0"}, "decompteNominatif": {"nonVotants": null, "pours": {"votant": [{"acteurRef": "PA793122", "mandatRef": "PM842369", "parDelegation": "false", "numPlace": "357"}, {"acteurRef": "PA795258", "mandatRef": "PM843794", "parDelegation": "false", "numPlace": "348"}, {"acteurRef": "PA721234", "mandatRef": "PM843692", "parDelegation": "false", "numPlace": "352"}]}, "contres": null, "abstentions": null}}}, {"organeRef": "PO845470", "nombreMembresGroupe": "35", "vote": {"positionMajoritaire": "pour", "decompteVoix": {"nonVotants": "0", "pour": "0", "contre": "0", "abstentions": "0", "nonVotantsVolontaires": "0"}, "decompteNominatif": {"nonVotants": null, "pours": null, "contres": null, "abstentions": null}}}, {"organeRef": "PO845485", "nombreMembresGroupe": "23", "vote": {"positionMajoritaire": "pour", "decompteVoix": {"nonVotants": "0", "pour": "2", "contre": "0", "abstentions": "0", "nonVotantsVolontaires": "0"}, "decompteNominatif": {"nonVotants": null, "pours": {"votant": [{"acteurRef": "PA720976", "mandatRef": "PM843764", "parDelegation": "false", "numPlace": "483"}, {"acteurRef": "PA721110", "mandatRef": "PM843782", "parDelegation": "false", "numPlace": "482"}]}, "contres": null, "abstentions": null}}}, {"organeRef": "PO872880", "nombreMembresGroupe": "17", "vote": {"positionMajoritaire": "pour", "decompteVoix": {"nonVotants": "0", "pour": "1", "contre": "0", "abstentions": "0", "nonVotantsVolontaires": "0"}, "decompteNominatif": {"nonVotants": null, "pours": {"votant": {"acteurRef": "PA840773", "mandatRef": "PM842456", "parDelegation": "false", "numPlace": "103"}}, "contres": null, "abstentions": null}}}, {"organeRef": "PO845514", "nombreMembresGroupe": "17", "vote": {"positionMajoritaire": "pour", "decompteVoix": {"nonVotants": "0", "pour": "4", "contre": "0", "abstentions": "0", "nonVotantsVolontaires": "0"}, "decompteNominatif": {"nonVotants": null, "pours": {"votant": [{"acteurRef": "PA795820", "mandatRef": "PM843713", "parDelegation": "false", "numPlace": "581"}, {"acteurRef": "PA721270", "mandatRef": "PM840438", "parDelegation": "false", "numPlace": "583"}, {"acteurRef": "PA795240", "mandatRef": "PM843785", "parDelegation": "false", "numPlace": "580"}, {"acteurRef": "PA842299", "mandatRef": "PM843791", "parDelegation": "false", "numPlace": "582"}]}, "contres": null, "abstentions": null}}}, {"organeRef": "PO840056", "nombreMembresGroupe": "10", "vote": {"positionMajoritaire": "pour", "decompteVoix": {"nonVotants": "0", "pour": "0", "contre": "0", "abstentions": "0", "nonVotantsVolontaires": "0"}, "decompteNominatif": {"nonVotants": null, "pours": null, "contres": null, "abstentions": null}}}]}}}, "miseAuPoint": {"nonVotants": [null, null], "pours": null, "abstentions": [null, null], "nonVotantsVolontaires": [null, null], "contres": null, "dysfonctionnement": {"nonVotants": null, "pour": null, "contre": null, "abstentions": null, "nonVotantsVolontaires": null}}, "lieuVote": "H\u00e9micycle"}}